{
  "project_info": {
    "project_number": "420856537968",
    "project_id": "imagetotext-34f2b",
    "storage_bucket": "imagetotext-34f2b.appspot.com"
  },
  "client": [
    {
      "client_info": {
        "mobilesdk_app_id": "1:420856537968:android:97054b437d38359c2025b5",
        "android_client_info": {
          "package_name": "com.example.imagetotext"
        }
      },
      "oauth_client": [
        {
          "client_id": "420856537968-dg7feeo5lkdibls63a9qu1iibkb5muph.apps.googleusercontent.com",
          "client_type": 3
        }
      ],
      "api_key": [
        {
          "current_key": "AIzaSyB0YryXKxZCdrXpMjMvW5v3zZCfZFzVXqQ"
        }
      ],
      "services": {
        "appinvite_service": {
          "other_platform_oauth_client": [
            {
              "client_id": "420856537968-dg7feeo5lkdibls63a9qu1iibkb5muph.apps.googleusercontent.com",
              "client_type": 3
            }
          ]
        }
      }
    }
  ],
  "configuration_version": "1"
}